spoor/__init__.py
spoor/config.py
spoor/exporter.py
spoor/statistics.py
spoor/storage.py
spoor/tracker.py
spoor/utils.py
spoor-0.6.0.dist-info/WHEEL
spoor-0.6.0.dist-info/METADATA
spoor-0.6.0.dist-info/RECORD
